gstpy/__init__.py
gstpy/main.py
gstpy-0.1.3.dist-info/METADATA
gstpy-0.1.3.dist-info/WHEEL
gstpy-0.1.3.dist-info/licenses/LICENSE
gstpy-0.1.3.dist-info/RECORD
