Metadata-Version: 2.4
Name: gstpy
Version: 0.1.3
Summary: gstpy is a simple and flexible Python module that allows you to calculate GST (Goods and Services Tax) in both exclusive and inclusive modes. It provides the option to return results as list values (ideal for developers) or display them in a formatted tabular output (perfect for CLI and reports).
Project-URL: Homepage, https://github.com/ankush-dhingraa/gstpy
Project-URL: Issues, https://github.com/ankush-dhingraa/gstpy/issues
Author-email: Ankush Dhingra <ankushkumar20024@gmail.com>
License-Expression: MIT
License-File: LICENSE
Classifier: Operating System :: OS Independent
Classifier: Programming Language :: Python :: 3
Requires-Python: >=3.7
Requires-Dist: tabulate==0.9.0
